acrocord/__init__.py
acrocord/databasepg.py
acrocord/factory/__init__.py
acrocord/factory/table.py
acrocord/misc/__init__.py
acrocord/misc/execution.py
acrocord/test/__init__.py
acrocord/test/constraints.py
acrocord/utils/__init__.py
acrocord/utils/auxiliaries.py
acrocord/utils/cache.py
acrocord/utils/connect.py
acrocord/utils/getpassword.py
acrocord/utils/insert.py
acrocord/utils/logger.py
acrocord/utils/monitoring.py
acrocord/utils/types.py
acrocord-2023.3.4.dist-info/LICENSE
acrocord-2023.3.4.dist-info/METADATA
acrocord-2023.3.4.dist-info/WHEEL
acrocord-2023.3.4.dist-info/top_level.txt
acrocord-2023.3.4.dist-info/RECORD
