Metadata-Version: 2.1
Name: acrocord
Version: 2023.3.4
Summary: Python API for PostreSQL database
Author-email: Eurobios <contact_ost@eurobios.com>
License: Apache License
Project-URL: repository, https://github.com/eurobios-scb/acrocord
Keywords: data,database,postgresql
Classifier: Programming Language :: Python
Classifier: Programming Language :: Python :: 3
Requires-Python: >=3.7
License-File: LICENSE
Requires-Dist: psycopg2 >2.9
Requires-Dist: numpy
Requires-Dist: pandas >=1.0
Requires-Dist: sqlalchemy >2
Requires-Dist: memory-profiler
Requires-Dist: termcolor >=1.0
Requires-Dist: xlsxwriter >=3.0.3
Requires-Dist: geopandas ==0.10.2
Requires-Dist: geoalchemy2 ==0.12.5
Requires-Dist: asyncpg
